{
  "movieList":[
    {
      "id": 1,
      "name":"Shimada Mayu",
      "image":"images/dammy.png",
      "url":"//www.youtube.com/embed/x-79hDn8RCA?autoplay=1",
      "caption":"あ"
    },
    {
      "id": 2,
      "name":"Shimada Mayu",
      "image":"images/dammy.png",
      "url":"//www.youtube.com/embed/MJqAhbhffpU?autoplay=1",
      "caption":"い"
    },
    {
      "id": 3,
      "name":"Shimada Mayu",
      "image":"images/dammy.png",
      "url":"//www.youtube.com/embed/LIlZCmETvsY?autoplay=1",
      "caption":"う"
    },
    {
      "id": 4,
      "name":"Shimada Mayu",
      "image":"images/dammy.png",
      "url":"//www.youtube.com/embed/iXREolaN934?autoplay=1",
      "caption":"え"
    },
    {
      "id": 5,
      "name":"Shimada Mayu",
      "image":"images/dammy.png",
      "url":"//www.youtube.com/embed/2bJ49dOSP9o?autoplay=1",
      "caption":"お"
    },
    {
      "id": 6,
      "name":"Shimada Mayu",
      "image":"images/dammy.png",
      "url":"//www.youtube.com/embed/LZ6-PfPx0EM?autoplay=1",
      "caption":"か"
    },
    {
      "id": 7,
      "name":"Shimada Mayu",
      "image":"images/dammy.png",
      "url":"//www.youtube.com/embed/pWY-S_wGlOs?autoplay=1",
      "caption":"き"
    }
  ]
}
